{"standings": [{"nickname": "Manchester City", "shortname": "MCI", "position": 1, "played": 28, "points": 69, "won": 22, "drawn": 3, "lost": 3, "goals_for": 68, "goals_against": 18}, {"nickname": "Liverpool", "shortname": "LIV", "position": 2, "played": 28, "points": 66, "won": 20, "drawn": 6, "lost": 2, "goals_for": 73, "goals_against": 20}, {"nickname": "Chelsea", "shortname": "CHE", "position": 3, "played": 28, "points": 59, "won": 17, "drawn": 8, "lost": 3, "goals_for": 57, "goals_against": 19}, {"nickname": "Arsenal", "shortname": "ARS", "position": 4, "played": 26, "points": 51, "won": 16, "drawn": 3, "lost": 7, "goals_for": 43, "goals_against": 29}, {"nickname": "Manchester United", "shortname": "MUN", "position": 5, "played": 29, "points": 50, "won": 14, "drawn": 8, "lost": 7, "goals_for": 48, "goals_against": 40}, {"nickname": "West Ham United", "shortname": "WHU", "position": 6, "played": 29, "points": 48, "won": 14, "drawn": 6, "lost": 9, "goals_for": 48, "goals_against": 36}, {"nickname": "Wolverhampton Wanderers", "shortname": "WOL", "position": 7, "played": 29, "points": 46, "won": 14, "drawn": 4, "lost": 11, "goals_for": 29, "goals_against": 23}, {"nickname": "Tottenham Hotspur", "shortname": "TOT", "position": 8, "played": 27, "points": 45, "won": 14, "drawn": 3, "lost": 10, "goals_for": 42, "goals_against": 35}, {"nickname": "Aston Villa", "shortname": "AVL", "position": 9, "played": 28, "points": 36, "won": 11, "drawn": 3, "lost": 14, "goals_for": 41, "goals_against": 39}, {"nickname": "Southampton", "shortname": "SOU", "position": 10, "played": 29, "points": 35, "won": 8, "drawn": 11, "lost": 10, "goals_for": 36, "goals_against": 45}, {"nickname": "Crystal Palace", "shortname": "CRY", "position": 11, "played": 28, "points": 33, "won": 7, "drawn": 12, "lost": 9, "goals_for": 39, "goals_against": 38}, {"nickname": "Leicester City", "shortname": "LEI", "position": 12, "played": 26, "points": 33, "won": 9, "drawn": 6, "lost": 11, "goals_for": 40, "goals_against": 45}, {"nickname": "Brighton and Hove Albion", "shortname": "BHA", "position": 13, "played": 28, "points": 33, "won": 7, "drawn": 12, "lost": 9, "goals_for": 26, "goals_against": 34}, {"nickname": "Newcastle United", "shortname": "NEW", "position": 14, "played": 28, "points": 31, "won": 7, "drawn": 10, "lost": 11, "goals_for": 32, "goals_against": 48}, {"nickname": "Brentford", "shortname": "BRE", "position": 15, "played": 29, "points": 30, "won": 8, "drawn": 6, "lost": 15, "goals_for": 32, "goals_against": 45}, {"nickname": "Leeds United", "shortname": "LEE", "position": 16, "played": 29, "points": 26, "won": 6, "drawn": 8, "lost": 15, "goals_for": 31, "goals_against": 65}, {"nickname": "Everton", "shortname": "EVE", "position": 17, "played": 26, "points": 22, "won": 6, "drawn": 4, "lost": 16, "goals_for": 28, "goals_against": 47}, {"nickname": "Watford", "shortname": "WAT", "position": 18, "played": 29, "points": 22, "won": 6, "drawn": 4, "lost": 19, "goals_for": 29, "goals_against": 55}, {"nickname": "Burnley", "shortname": "BUR", "position": 19, "played": 27, "points": 21, "won": 3, "drawn": 12, "lost": 12, "goals_for": 22, "goals_against": 38}, {"nickname": "Norwich City", "shortname": "NOR", "position": 20, "played": 29, "points": 17, "won": 4, "drawn": 5, "lost": 20, "goals_for": 18, "goals_against": 63}]}